odometer/__init__.py
odometer/__release__.py
odometer/date_odometer.py
odometer/exceptions.py
odometer/odometer.py
odometer-0.1.0.dist-info/LICENSE
odometer-0.1.0.dist-info/METADATA
odometer-0.1.0.dist-info/WHEEL
odometer-0.1.0.dist-info/RECORD
