Metadata-Version: 2.1
Name: odometer
Version: 0.1.0
Summary: odometer classes
Home-page: https://gitlab.com/Anonym0u5/odometer
License: GPL-3.0-or-later
Author: An0nym0u5
Author-email: anonym0u5@disroot.org
Maintainer: An0nym0u5
Maintainer-email: anonym0u5@disroot.org
Requires-Python: >=3.11,<4.0
Classifier: Development Status :: 3 - Alpha
Classifier: Environment :: Other Environment
Classifier: Intended Audience :: Developers
Classifier: License :: OSI Approved :: GNU General Public License v3 or later (GPLv3+)
Classifier: Natural Language :: English
Classifier: Operating System :: OS Independent
Classifier: Programming Language :: Python :: 3
Classifier: Programming Language :: Python :: 3.11
Classifier: Programming Language :: Python :: 3
Classifier: Topic :: Software Development
Classifier: Topic :: Software Development :: Libraries
Classifier: Topic :: Software Development :: Libraries :: Python Modules
Project-URL: Documentation, https://odometer.readthedocs.io/en/latest/
Project-URL: Repository, https://gitlab.com/Anonym0u5/odometer.git
